Workbook

Sheet Start here
A1: The ADHD Budget Template
A2: Free from jmstruijk.com. Follows the structure of The ADHD Budget Planner.
A4: One hour, once
A5: 1. Bills: list every bill with its amount, the day it is due, and whether it is on autopay.
A6: 2. Money Map: enter what comes in each month and a figure for each flexible category.
A7: 3. Move anything marked No onto autopay, if you can. Each one is a due date you no longer have to remember.
A9: Ten minutes, once a week
A10: 4. Weekly check-in: write what you spent this week. The sheet compares it with your weekly money.
A11: 5. ADHD Tax log: add any late fee, forgotten subscription or replacement buy when it happens.
A13: If you miss a week, or a month
A14: Nothing breaks. The weeks are numbered rather than dated, so start again at the next row.
A16: Blue numbers are yours to change. Black numbers are worked out for you. Green ones come from another sheet.
A17: Amounts are in whatever currency you use. Nothing in this file is sent anywhere.

Sheet Bills
A1: Bills master list
A2: Every bill, with the day it is due. Getting these out of your head is the point.
A4: Bill | B4: Per month | C4: Due day (1-31) | D4: On autopay? | E4: Notes
A31: Total bills per month | B31: =SUM(B5:B29) -> 0
A32: Bills not on autopay | B32: =COUNTIFS(A5:A29,"<>",D5:D29,"<>Yes") -> 0

Sheet Money Map
A1: Money map
A2: One page for the month. Few categories on purpose: every extra one is another decision.
B4: Per month | C4: Note
A5: Take-home income | C5: What actually arrives, after tax.
A7: Bills | B7: =Bills!$B$31 -> 0 | C7: From the Bills sheet.
A8: Groceries
A9: Getting around | C9: Fuel, fares, parking.
A10: Everything else | C10: Kept as one figure. Splitting it further rarely survives a month.
A11: ADHD tax buffer | C11: Late fees, forgotten subscriptions, replacements. Plan for it. The ADHD Tax Calculator at jmstruijk.com/tools/ gives your own figure.
A12: Savings | C12: Moved automatically on payday, ideally.
A14: Total going out | B14: =SUM(B7:B12) -> 0
A15: Left over | B15: =B5-B14 -> 0 | C15: =IF(B5=0,"Enter your income first.",IF(B15<0,"The plan spends more than comes in. Trim a flexible figure.","Balanced.")) -> Enter your income first.
A17: Weeks in a month | B17: =52/12 -> 4.3333333 | C17: 52 weeks over 12 months, so a month is a little over four weeks.
A18: Weekly spending money | B18: =SUM(B8:B10)/B17 -> 0 | C18: Groceries, getting around and everything else, per week. A week is easier to keep track of than a month.

Sheet Weekly check-in
A1: Weekly check-in
A2: Ten minutes. Numbered rather than dated, so a missed week costs nothing.
A4: Week | B4: Week starting | C4: Spent this week | D4: Weekly money | E4: Difference | F4: One thing to change
A5: 1 | D5: ='Money Map'!$B$18 -> 0 | E5: =IF(C5="","",D5-C5)
A6: 2 | D6: ='Money Map'!$B$18 -> 0 | E6: =IF(C6="","",D6-C6)
A7: 3 | D7: ='Money Map'!$B$18 -> 0 | E7: =IF(C7="","",D7-C7)
A8: 4 | D8: ='Money Map'!$B$18 -> 0 | E8: =IF(C8="","",D8-C8)
A9: 5 | D9: ='Money Map'!$B$18 -> 0 | E9: =IF(C9="","",D9-C9)
A10: 6 | D10: ='Money Map'!$B$18 -> 0 | E10: =IF(C10="","",D10-C10)
A11: 7 | D11: ='Money Map'!$B$18 -> 0 | E11: =IF(C11="","",D11-C11)
A12: 8 | D12: ='Money Map'!$B$18 -> 0 | E12: =IF(C12="","",D12-C12)
A13: 9 | D13: ='Money Map'!$B$18 -> 0 | E13: =IF(C13="","",D13-C13)
A14: 10 | D14: ='Money Map'!$B$18 -> 0 | E14: =IF(C14="","",D14-C14)
A15: 11 | D15: ='Money Map'!$B$18 -> 0 | E15: =IF(C15="","",D15-C15)
A16: 12 | D16: ='Money Map'!$B$18 -> 0 | E16: =IF(C16="","",D16-C16)
... A56: 52 | D56: ='Money Map'!$B$18 -> 0 | E56: =IF(C56="","",D56-C56)

Sheet ADHD Tax log
A1: ADHD Tax log
A2: Write it down when it happens, without judging it. The pattern is what is useful.
A4: Date | B4: What happened | C4: Type | D4: Amount | E4: Could autopay or a reminder stop it?
A66: Total so far | D66: =SUM(D5:D64) -> 0
C68: Late fee | D68: =SUMIF(C5:C64,"Late fee",D5:D64) -> 0
C69: Forgotten subscription | D69: =SUMIF(C5:C64,"Forgotten subscription",D5:D64) -> 0
C70: Impulse buy | D70: =SUMIF(C5:C64,"Impulse buy",D5:D64) -> 0
C71: Replacement | D71: =SUMIF(C5:C64,"Replacement",D5:D64) -> 0
C72: Convenience | D72: =SUMIF(C5:C64,"Convenience",D5:D64) -> 0
C73: Other | D73: =SUMIF(C5:C64,"Other",D5:D64) -> 0
